nam_pytorch/__init__.py
nam_pytorch/nam_pytorch.py
nam_pytorch-0.0.1.dist-info/LICENSE
nam_pytorch-0.0.1.dist-info/METADATA
nam_pytorch-0.0.1.dist-info/WHEEL
nam_pytorch-0.0.1.dist-info/top_level.txt
nam_pytorch-0.0.1.dist-info/RECORD
