Metadata-Version: 2.1
Name: nam-pytorch
Version: 0.0.1
Summary: Neural Additive Models (NAM) - Pytorch
Home-page: https://github.com/rish-16/nam-pytorch
Author: Rishabh Anand
Author-email: mail.rishabh.anand@gmail.com
License: MIT
Keywords: artificial intelligence,deep learning,nam,neural additive models,generalized additive models
Platform: UNKNOWN
Classifier: Development Status :: 4 - Beta
Classifier: Intended Audience :: Developers
Classifier: Topic :: Scientific/Engineering :: Artificial Intelligence
Classifier: License :: OSI Approved :: MIT License
Classifier: Programming Language :: Python :: 3.6
Requires-Dist: torch (>=1.6)
